<?xml version="1.0" encoding="UTF-8"?>
<!DOCTYPE mapper PUBLIC "-//mybatis.org//DTD Mapper 3.0//EN" "http://mybatis.org/dtd/mybatis-3-mapper.dtd">
<mapper namespace="workflow.engine.mapper.RequestMapper">
    
    <resultMap id="BaseResultMap" type="Request">
        <id column="id" jdbcType="INTEGER" property="id" />
        <result property="process" jdbcType="INTEGER" column="process_id" />
        <result property="user" jdbcType="INTEGER" column="user_id" />
        <result property="state" jdbcType="INTEGER" column="current_state_id" />
        <result property="title" jdbcType="VARCHAR" column="title" />
    </resultMap>
    
    <sql id="Base_Column_List">
        id, process_id, title, user_id, current_state_id
    </sql>
    
    <sql id="Table_Name">
        request
    </sql>
    
    <sql id="Primary_Key">
        id
    </sql>
    
    <select id="getRequest" resultMap="BaseResultMap">
        select <include refid="Base_Column_List" /> 
        from <include refid="Table_Name" /> 
        where <include refid="Primary_Key" /> = #{id}
    </select>
    
</mapper>